faciescanner/__init__.py
faciescanner/data_input.py
faciescanner-1.0.0.dist-info/LICENSE
faciescanner-1.0.0.dist-info/METADATA
faciescanner-1.0.0.dist-info/WHEEL
faciescanner-1.0.0.dist-info/top_level.txt
faciescanner-1.0.0.dist-info/RECORD
