Metadata-Version: 2.1
Name: faciescanner
Version: 1.0.0
Summary: This package is created to classify facies using borehole image array in Techlog, output prediction result.
Home-page: UNKNOWN
Author: Xiaohu Jiang
License: UNKNOWN
Platform: UNKNOWN
Classifier: Programming Language :: Python :: 3
Classifier: License :: OSI Approved :: MIT License
Classifier: Operating System :: OS Independent
Requires-Dist: numpy (==1.24.2)
Requires-Dist: pandas (==1.5.3)
Requires-Dist: Pillow (==9.1.1)
Requires-Dist: dataiku-api-client (==11.4.0)
